sshconf.py
sshconf-0.2.6.dist-info/LICENSE
sshconf-0.2.6.dist-info/WHEEL
sshconf-0.2.6.dist-info/METADATA
sshconf-0.2.6.dist-info/RECORD
