Metadata-Version: 2.1
Name: sshconf
Version: 0.2.6
Summary: Lightweight SSH config library.
Keywords: ssh,config
Author-email: Søren A D <sorend@gmail.com>
Requires-Python: >=3.5
Classifier: License :: OSI Approved :: MIT License
Classifier: Programming Language :: Python :: 3
Classifier: Topic :: Software Development :: Libraries :: Python Modules
Classifier: Topic :: Software Development :: Libraries
Requires-Dist: pytest ; extra == "test"
Requires-Dist: pytest-cov ; extra == "test"
Requires-Dist: codecov ; extra == "test"
Project-URL: homepage, https://github.com/sorend/sshconf
Provides-Extra: test
